multistage/__init__.py
multistage/_io_utils.py
multistage/_multistage.py
multistage/_plot.py
multistage/_utils.py
multistage/_version.py
multistage-0.1b0.dist-info/licenses/LICENSE
multistage-0.1b0.dist-info/METADATA
multistage-0.1b0.dist-info/WHEEL
multistage-0.1b0.dist-info/top_level.txt
multistage-0.1b0.dist-info/RECORD
