Metadata-Version: 2.4
Name: multistage
Version: 0.1b0
Summary: Multistage neural networks with JAX
Home-page: https://github.com/unalmis/multistage
Author: Kaya Unalmis
Author-email: kunalmis@stanford.edu
License: MIT
Project-URL: Issues Tracker, https://github.com/unalmis/multistage/issues
Project-URL: Contributing, https://github.com/unalmis/multistage/blob/master/CONTRIBUTING.rst
Project-URL: Source Code, https://github.com/unalmis/multistage/
Project-URL: Documentation, https://unalmis.github.io/multistage/
Keywords: neural network optimization pde inverse
Classifier: Development Status :: 3 - Alpha
Classifier: Intended Audience :: Science/Research
Classifier: License :: OSI Approved :: MIT License
Classifier: Natural Language :: English
Classifier: Programming Language :: Python :: 3
Classifier: Programming Language :: Python :: 3.10
Classifier: Programming Language :: Python :: 3.11
Classifier: Programming Language :: Python :: 3.12
Classifier: Programming Language :: Python :: 3.13
Classifier: Topic :: Scientific/Engineering
Classifier: Topic :: Scientific/Engineering :: Mathematics
Classifier: Typing :: Typed
Requires-Python: >=3.10
License-File: LICENSE
Requires-Dist: equinox>=0.13.1
Requires-Dist: lineax
Requires-Dist: interpax_fft
Requires-Dist: jax!=0.5.1,!=0.5.2,!=0.6.0,!=0.7.1,<=0.8.1,>=0.5.0
Requires-Dist: matplotlib
Requires-Dist: numpy
Requires-Dist: optax
Requires-Dist: optimistix
Requires-Dist: orbax-checkpoint
Requires-Dist: paramax
Dynamic: author
Dynamic: author-email
Dynamic: classifier
Dynamic: description
Dynamic: description-content-type
Dynamic: home-page
Dynamic: keywords
Dynamic: license
Dynamic: license-file
Dynamic: project-url
Dynamic: requires-dist
Dynamic: requires-python
Dynamic: summary
